README.rst
setup.py
testlap/__init__.py
testlap.egg-info/PKG-INFO
testlap.egg-info/SOURCES.txt
testlap.egg-info/dependency_links.txt
testlap.egg-info/requires.txt
testlap.egg-info/top_level.txt