Metadata-Version: 1.1
Name: testlap
Version: 1.0.0
Summary: A Python framework to measure and compare the execution speed of different methods in a class.
Home-page: https://github.com/smetj/testlap
Author: Jelle Smet
Author-email: development@smetj.net
License: UNKNOWN
Download-URL: https://github.com/smetj/molog/tarball/wishbone_based
Platform: Any
Classifier: Development Status :: 3 - Alpha
Classifier: License :: OSI Approved :: Apache Software License
Classifier: Programming Language :: Python
Classifier: Programming Language :: Python :: 2
Classifier: Programming Language :: Python :: 3
